ipyvue_time_series/__init__.py
ipyvue_time_series/buffering_client.py
ipyvue_time_series/client.py
ipyvue_time_series/comm_widget.py
ipyvue_time_series/force_load.py
ipyvue_time_series/time_series.py
ipyvue_time_series/labextension/package.json
ipyvue_time_series/labextension/static/261.36c099dfd87db964148b.js
ipyvue_time_series/labextension/static/261.73aa3882ff4e9257e267.js
ipyvue_time_series/labextension/static/261.b485ab5730bb517dcb61.js
ipyvue_time_series/labextension/static/568.956310d0e4ed278c6e8d.js
ipyvue_time_series/labextension/static/568.d713ce5ac7494794a864.js
ipyvue_time_series/labextension/static/568.f0c4b8713467a0b35ad0.js
ipyvue_time_series/labextension/static/remoteEntry.6bbeb915294f9c40cfed.js
ipyvue_time_series/labextension/static/remoteEntry.8b49137fc6e15416e2f5.js
ipyvue_time_series/labextension/static/remoteEntry.8cd130e094f27df9d906.js
ipyvue_time_series/labextension/static/style.js
ipyvue_time_series/labextension/static/third-party-licenses.json
ipyvue_time_series/nbextension/extension.js
ipyvue_time_series/nbextension/index.js
ipyvue_time_series-1.0.2.data/data/etc/jupyter/nbconfig/notebook.d/ipyvue-time-series.json
ipyvue_time_series-1.0.2.data/data/share/jupyter/labextensions/ipyvue-time-series/install.json
ipyvue_time_series-1.0.2.data/data/share/jupyter/labextensions/ipyvue-time-series/package.json
ipyvue_time_series-1.0.2.data/data/share/jupyter/labextensions/ipyvue-time-series/static/261.73aa3882ff4e9257e267.js
ipyvue_time_series-1.0.2.data/data/share/jupyter/labextensions/ipyvue-time-series/static/568.d713ce5ac7494794a864.js
ipyvue_time_series-1.0.2.data/data/share/jupyter/labextensions/ipyvue-time-series/static/remoteEntry.8b49137fc6e15416e2f5.js
ipyvue_time_series-1.0.2.data/data/share/jupyter/labextensions/ipyvue-time-series/static/style.js
ipyvue_time_series-1.0.2.data/data/share/jupyter/labextensions/ipyvue-time-series/static/third-party-licenses.json
ipyvue_time_series-1.0.2.dist-info/METADATA
ipyvue_time_series-1.0.2.dist-info/WHEEL
ipyvue_time_series-1.0.2.dist-info/top_level.txt
ipyvue_time_series-1.0.2.dist-info/RECORD
