Metadata-Version: 2.1
Name: ipyvue-time-series
Version: 1.0.2
Summary: Real-Time Plots in Jupyter Notebooks and JupyterLab
Home-page: https://github.com/saraedum/ipyvue-time-series
Author: Julian Rüth
Author-email: julian.rueth@fsfe.org
License: UNKNOWN
Keywords: ipython,jupyter,widgets
Platform: UNKNOWN
Classifier: Development Status :: 4 - Beta
Classifier: Framework :: IPython
Classifier: License :: OSI Approved :: MIT License
Classifier: Intended Audience :: Developers
Classifier: Intended Audience :: Science/Research
Classifier: Topic :: Multimedia :: Graphics
Classifier: Programming Language :: Python :: 3.6
Classifier: Programming Language :: Python :: 3.7
Classifier: Programming Language :: Python :: 3.8
Classifier: Programming Language :: Python :: 3.9
Requires-Dist: ipyvue-remote-component (>=1.1.0)
